MANIFEST
MANIFEST.in
README.md
setup.cfg
setup.py
FileOrganiser/LICENSE
FileOrganiser/__init__.py
FileOrganiser/__main__.py
FileOrganiser/fileorganiser.py
FileOrganiser.egg-info/PKG-INFO
FileOrganiser.egg-info/SOURCES.txt
FileOrganiser.egg-info/dependency_links.txt
FileOrganiser.egg-info/requires.txt
FileOrganiser.egg-info/top_level.txt
FileOrganiser/modes/__init__.py
FileOrganiser/modes/another.py
FileOrganiser/modes/extensions.py
FileOrganiser/modes/generic_script.py
FileOrganiser/modes/regex.py
FileOrganiser/modes/script.py
FileOrganiser/modes/__pycache__/__init__.cpython-310.pyc
FileOrganiser/modes/__pycache__/extensions.cpython-310.pyc
FileOrganiser/modes/__pycache__/regex.cpython-310.pyc
FileOrganiser/modes/__pycache__/script.cpython-310.pyc
exampleRules/Documents/rules01.toml
exampleRules/Documents/rules02.toml
exampleRules/Downloads/rules.toml