Metadata-Version: 2.1
Name: FileOrganiser
Version: 1.0.11
Summary: A Modular tool to keep directories organised
Home-page: https://github.com/lifesgood123/FileOrganiser
Author: Ellie Mae Galyean
Author-email: tggalyea@uncg.edu
License: GPL
Download-URL: https://github.com/Lifesgood123/FileOrganiser/archive/refs/tags/1.0.6.zip
Keywords: files,organization,productivity,daemon
Platform: UNKNOWN
Classifier: Development Status :: 5 - Production/Stable
Classifier: Intended Audience :: End Users/Desktop
Classifier: License :: Freely Distributable
Classifier: Programming Language :: Python :: 3.8
